.bumpversion.cfg
.cookiecutterrc
.coveragerc
.editorconfig
.travis.yml
AUTHORS.rst
CHANGELOG.rst
CONTRIBUTING.rst
LICENSE
MANIFEST.in
README.rst
appveyor.yml
setup.cfg
setup.py
tox.ini
ci/appveyor-bootstrap.py
ci/appveyor-download.py
ci/appveyor-with-compiler.cmd
ci/bootstrap.py
ci/templates/.travis.yml
ci/templates/appveyor.yml
ci/templates/tox.ini
docs/authors.rst
docs/changelog.rst
docs/conf.py
docs/contributing.rst
docs/index.rst
docs/installation.rst
docs/readme.rst
docs/requirements.txt
docs/spelling_wordlist.txt
docs/usage.rst
docs/reference/challenge_me.rst
docs/reference/index.rst
src/main.py
src/challenge_me/__init__.py
src/challenge_me/__main__.py
src/challenge_me/challenge_me.py
src/challenge_me/cli.py
src/challenge_me.egg-info/PKG-INFO
src/challenge_me.egg-info/SOURCES.txt
src/challenge_me.egg-info/dependency_links.txt
src/challenge_me.egg-info/entry_points.txt
src/challenge_me.egg-info/not-zip-safe
src/challenge_me.egg-info/requires.txt
src/challenge_me.egg-info/top_level.txt
src/challenge_me/challenges/array.yaml
src/challenge_me/challenges/bit.yaml
src/challenge_me/challenges/graph.yaml
src/challenge_me/challenges/linked_list.yaml
src/challenge_me/challenges/other.yaml
src/challenge_me/challenges/recursion.yaml
src/challenge_me/challenges/searching.yaml
src/challenge_me/challenges/sorting.yaml
src/challenge_me/challenges/stack.yaml
src/challenge_me/challenges/string.yaml
src/challenge_me/challenges/tree.yaml
src/challenge_me/templates/python.template
tests/test_challenge_me.py